flake8_executable/__init__.py
flake8_executable/_version.py
flake8_executable-2.1.3.data/data/COPYING
flake8_executable-2.1.3.data/data/COPYING.GPL
flake8_executable-2.1.3.dist-info/COPYING
flake8_executable-2.1.3.dist-info/COPYING.GPL
flake8_executable-2.1.3.dist-info/METADATA
flake8_executable-2.1.3.dist-info/WHEEL
flake8_executable-2.1.3.dist-info/entry_points.txt
flake8_executable-2.1.3.dist-info/top_level.txt
flake8_executable-2.1.3.dist-info/RECORD
