Metadata-Version: 2.1
Name: flake8-executable
Version: 2.1.3
Summary: A Flake8 plugin for checking executable permissions and shebangs.
Home-page: https://github.com/xuhdev/flake8-executable
Author: Hong Xu
Author-email: hong@topbug.net
License: LGPL v3+
Keywords: flake8 linter qa
Classifier: Environment :: Console
Classifier: Framework :: Flake8
Classifier: Intended Audience :: Developers
Classifier: License :: OSI Approved :: GNU Lesser General Public License v3 or later (LGPLv3+)
Classifier: Operating System :: OS Independent
Classifier: Programming Language :: Python
Classifier: Programming Language :: Python :: 3
Classifier: Programming Language :: Python :: 3.7
Classifier: Programming Language :: Python :: 3.8
Classifier: Programming Language :: Python :: 3.9
Classifier: Programming Language :: Python :: 3.10
Classifier: Programming Language :: Python :: 3.11
Classifier: Programming Language :: Python :: 3 :: Only
Classifier: Topic :: Software Development :: Libraries :: Python Modules
Classifier: Topic :: Software Development :: Quality Assurance
Requires-Python: >=3.6
License-File: COPYING
License-File: COPYING.GPL
